pvlib/__init__.py
pvlib/_deprecation.py
pvlib/albedo.py
pvlib/atmosphere.py
pvlib/clearsky.py
pvlib/iam.py
pvlib/inverter.py
pvlib/irradiance.py
pvlib/location.py
pvlib/modelchain.py
pvlib/pvarray.py
pvlib/pvsystem.py
pvlib/scaling.py
pvlib/shading.py
pvlib/singlediode.py
pvlib/snow.py
pvlib/soiling.py
pvlib/solarposition.py
pvlib/spa.py
pvlib/temperature.py
pvlib/tools.py
pvlib/tracking.py
pvlib/transformer.py
pvlib/version.py
pvlib/bifacial/__init__.py
pvlib/bifacial/infinite_sheds.py
pvlib/bifacial/loss_models.py
pvlib/bifacial/pvfactors.py
pvlib/bifacial/utils.py
pvlib/data/12839.tm2
pvlib/data/703165TY.csv
pvlib/data/723170TYA.CSV
pvlib/data/ASTMG173.csv
pvlib/data/Altitude.h5
pvlib/data/BIRD_08_16_2012.csv
pvlib/data/BIRD_08_16_2012_patm.csv
"pvlib/data/Burlington, United States SolarAnywhere Time Series 2021 Lat_44_465 Lon_-73_205 TMY3 format.csv"
"pvlib/data/Burlington, United States SolarAnywhere Time Series 20210101 to 20210103 Lat_44_4675 Lon_-73_2075 SA format.csv"
"pvlib/data/Burlington, United States SolarAnywhere Typical GHI Year Lat_44_465 Lon_-73_205 SA format.csv"
pvlib/data/CPS SCH275KTL-DO-US-800-250kW_275kVA_1.OND
pvlib/data/CRNS0101-05-2019-AZ_Tucson_11_W.txt
pvlib/data/CRN_with_problems.txt
pvlib/data/ET-M772BH550GL.PAN
pvlib/data/LinkeTurbidities.h5
pvlib/data/NLD_Amsterdam062400_IWEC.epw
pvlib/data/PVsyst_demo.csv
pvlib/data/PVsyst_demo_model.csv
pvlib/data/SRML-day-EUPO1801.txt
pvlib/data/abq19056.dat
pvlib/data/adr-library-cec-inverters-2019-03-05.csv
pvlib/data/aod550_tcwv_20121101_test.nc
pvlib/data/bishop88_numerical_precision.csv
pvlib/data/bsrn-lr0100-pay0616.dat
pvlib/data/bsrn-pay0616.dat.gz
pvlib/data/cams_mcclear_1min_verbose.csv
pvlib/data/cams_mcclear_monthly.csv
pvlib/data/cams_radiation_1min_verbose.csv
pvlib/data/cams_radiation_monthly.csv
pvlib/data/detect_clearsky_data.csv
pvlib/data/detect_clearsky_threshold_data.csv
pvlib/data/greensboro_kimber_soil_manwash.dat
pvlib/data/greensboro_kimber_soil_nowash.dat
pvlib-0.11.1.dist-info/AUTHORS.md
pvlib-0.11.1.dist-info/LICENSE
pvlib-0.11.1.dist-info/METADATA
pvlib-0.11.1.dist-info/WHEEL
pvlib-0.11.1.dist-info/top_level.txt
pvlib-0.11.1.dist-info/RECORD
