Metadata-Version: 2.1
Name: pvlib
Version: 0.11.1
Summary: A set of functions and classes for simulating the performance of photovoltaic energy systems.
Home-page: https://github.com/pvlib/pvlib-python
Author-email: pvlib python Developers <pvlib-admin@googlegroups.com>
License: BSD-3-Clause
Project-URL: Bug Tracker, https://github.com/pvlib/pvlib-python/issues
Project-URL: Documentation, https://pvlib-python.readthedocs.io/
Project-URL: Source Code, https://github.com/pvlib/pvlib-python
Classifier: Development Status :: 4 - Beta
Classifier: License :: OSI Approved :: BSD License
Classifier: Operating System :: OS Independent
Classifier: Intended Audience :: Science/Research
Classifier: Programming Language :: Python
Classifier: Programming Language :: Python :: 3
Classifier: Topic :: Scientific/Engineering
Requires-Python: >=3.9
License-File: LICENSE
License-File: AUTHORS.md
Requires-Dist: numpy>=1.19.3
Requires-Dist: pandas>=1.3.0
Requires-Dist: pytz
Requires-Dist: requests
Requires-Dist: scipy>=1.6.0
Requires-Dist: h5py
Provides-Extra: optional
Requires-Dist: cython; extra == "optional"
Requires-Dist: ephem; extra == "optional"
Requires-Dist: nrel-pysam; extra == "optional"
Requires-Dist: numba>=0.17.0; extra == "optional"
Requires-Dist: solarfactors; extra == "optional"
Requires-Dist: statsmodels; extra == "optional"
Provides-Extra: doc
Requires-Dist: ipython; extra == "doc"
Requires-Dist: pickleshare; extra == "doc"
Requires-Dist: matplotlib; extra == "doc"
Requires-Dist: sphinx==7.3.7; extra == "doc"
Requires-Dist: pydata-sphinx-theme==0.15.4; extra == "doc"
Requires-Dist: sphinx-gallery; extra == "doc"
Requires-Dist: docutils==0.21; extra == "doc"
Requires-Dist: pillow; extra == "doc"
Requires-Dist: sphinx-toggleprompt==0.5.2; extra == "doc"
Requires-Dist: sphinx-favicon; extra == "doc"
Requires-Dist: solarfactors; extra == "doc"
Provides-Extra: test
Requires-Dist: pytest; extra == "test"
Requires-Dist: pytest-cov; extra == "test"
Requires-Dist: pytest-mock; extra == "test"
Requires-Dist: requests-mock; extra == "test"
Requires-Dist: pytest-timeout; extra == "test"
Requires-Dist: pytest-rerunfailures; extra == "test"
Requires-Dist: pytest-remotedata; extra == "test"
Requires-Dist: packaging; extra == "test"
Provides-Extra: all
Requires-Dist: pvlib[doc,optional,test]; extra == "all"
